{
  "overall_stats": {
    "message_count": 119527,
    "positive_count": 24762,
    "negative_count": 11609,
    "neutral_count": 81676,
    "total_sentiment_count": 13153,
    "average_polarity": 0.04595455107349982,
    "average_subjectivity": 0.19524863703627585
  },
  "time_series": [
    {
      "weekday": "Monday",
      "hour": "00",
      "message_count": 394,
      "positive_count": 97,
      "negative_count": 46,
      "neutral_count": 251,
      "total_sentiment_count": 51,
      "average_polarity": 0.049264875000915614,
      "average_subjectivity": 0.23162064810541974
    },
    {
      "weekday": "Monday",
      "hour": "01",
      "message_count": 160,
      "positive_count": 49,
      "negative_count": 15,
      "neutral_count": 96,
      "total_sentiment_count": 34,
      "average_polarity": 0.07030317290733956,
      "average_subjectivity": 0.240999582400624
    },
    {
      "weekday": "Monday",
      "hour": "02",
      "message_count": 74,
      "positive_count": 14,
      "negative_count": 7,
      "neutral_count": 53,
      "total_sentiment_count": 7,
      "average_polarity": 0.04413280975780977,
      "average_subjectivity": 0.1790631946881947
    },
    {
      "weekday": "Monday",
      "hour": "03",
      "message_count": 54,
      "positive_count": 19,
      "negative_count": 2,
      "neutral_count": 33,
      "total_sentiment_count": 17,
      "average_polarity": 0.12312885802469133,
      "average_subjectivity": 0.23748713991769546
    },
    {
      "weekday": "Monday",
      "hour": "04",
      "message_count": 35,
      "positive_count": 10,
      "negative_count": 6,
      "neutral_count": 19,
      "total_sentiment_count": 4,
      "average_polarity": 0.07011904761904762,
      "average_subjectivity": 0.2655952380952381
    },
    {
      "weekday": "Monday",
      "hour": "05",
      "message_count": 245,
      "positive_count": 59,
      "negative_count": 29,
      "neutral_count": 157,
      "total_sentiment_count": 30,
      "average_polarity": 0.05313345554672085,
      "average_subjectivity": 0.23260617103984457
    },
    {
      "weekday": "Monday",
      "hour": "06",
      "message_count": 270,
      "positive_count": 67,
      "negative_count": 26,
      "neutral_count": 177,
      "total_sentiment_count": 41,
      "average_polarity": 0.0592340802201913,
      "average_subjectivity": 0.21058350480109744
    },
    {
      "weekday": "Monday",
      "hour": "07",
      "message_count": 605,
      "positive_count": 166,
      "negative_count": 74,
      "neutral_count": 365,
      "total_sentiment_count": 92,
      "average_polarity": 0.07923336637727132,
      "average_subjectivity": 0.2421222442846409
    },
    {
      "weekday": "Monday",
      "hour": "08",
      "message_count": 682,
      "positive_count": 168,
      "negative_count": 88,
      "neutral_count": 426,
      "total_sentiment_count": 80,
      "average_polarity": 0.061411931685941994,
      "average_subjectivity": 0.24346144511375464
    },
    {
      "weekday": "Monday",
      "hour": "09",
      "message_count": 560,
      "positive_count": 128,
      "negative_count": 61,
      "neutral_count": 371,
      "total_sentiment_count": 67,
      "average_polarity": 0.05085931264551278,
      "average_subjectivity": 0.21627342665358681
    },
    {
      "weekday": "Monday",
      "hour": "10",
      "message_count": 677,
      "positive_count": 170,
      "negative_count": 61,
      "neutral_count": 446,
      "total_sentiment_count": 109,
      "average_polarity": 0.06811377617950735,
      "average_subjectivity": 0.22096843851755243
    },
    {
      "weekday": "Monday",
      "hour": "11",
      "message_count": 559,
      "positive_count": 138,
      "negative_count": 61,
      "neutral_count": 360,
      "total_sentiment_count": 77,
      "average_polarity": 0.06152392020124578,
      "average_subjectivity": 0.21214091381354352
    },
    {
      "weekday": "Monday",
      "hour": "12",
      "message_count": 602,
      "positive_count": 125,
      "negative_count": 57,
      "neutral_count": 420,
      "total_sentiment_count": 68,
      "average_polarity": 0.047517655194565495,
      "average_subjectivity": 0.20778530419684912
    },
    {
      "weekday": "Monday",
      "hour": "13",
      "message_count": 985,
      "positive_count": 230,
      "negative_count": 97,
      "neutral_count": 658,
      "total_sentiment_count": 133,
      "average_polarity": 0.056009903426147145,
      "average_subjectivity": 0.21671009369930688
    },
    {
      "weekday": "Monday",
      "hour": "14",
      "message_count": 919,
      "positive_count": 211,
      "negative_count": 89,
      "neutral_count": 619,
      "total_sentiment_count": 122,
      "average_polarity": 0.05193876429458589,
      "average_subjectivity": 0.2081679697906576
    },
    {
      "weekday": "Monday",
      "hour": "15",
      "message_count": 1408,
      "positive_count": 255,
      "negative_count": 144,
      "neutral_count": 1009,
      "total_sentiment_count": 111,
      "average_polarity": 0.0362447222644977,
      "average_subjectivity": 0.17899277250724335
    },
    {
      "weekday": "Monday",
      "hour": "16",
      "message_count": 1067,
      "positive_count": 214,
      "negative_count": 104,
      "neutral_count": 749,
      "total_sentiment_count": 110,
      "average_polarity": 0.0406029637590966,
      "average_subjectivity": 0.19376777514546972
    },
    {
      "weekday": "Monday",
      "hour": "17",
      "message_count": 930,
      "positive_count": 201,
      "negative_count": 74,
      "neutral_count": 655,
      "total_sentiment_count": 127,
      "average_polarity": 0.05276319491440458,
      "average_subjectivity": 0.18747300469343484
    },
    {
      "weekday": "Monday",
      "hour": "18",
      "message_count": 991,
      "positive_count": 174,
      "negative_count": 67,
      "neutral_count": 750,
      "total_sentiment_count": 107,
      "average_polarity": 0.04271658126602629,
      "average_subjectivity": 0.16379449618475858
    },
    {
      "weekday": "Monday",
      "hour": "19",
      "message_count": 1273,
      "positive_count": 265,
      "negative_count": 133,
      "neutral_count": 875,
      "total_sentiment_count": 132,
      "average_polarity": 0.03993915567535956,
      "average_subjectivity": 0.20267379880891248
    },
    {
      "weekday": "Monday",
      "hour": "20",
      "message_count": 1375,
      "positive_count": 259,
      "negative_count": 108,
      "neutral_count": 1008,
      "total_sentiment_count": 151,
      "average_polarity": 0.04008660129760407,
      "average_subjectivity": 0.1790354506120116
    },
    {
      "weekday": "Monday",
      "hour": "21",
      "message_count": 1011,
      "positive_count": 224,
      "negative_count": 90,
      "neutral_count": 697,
      "total_sentiment_count": 134,
      "average_polarity": 0.05261203124457331,
      "average_subjectivity": 0.1876179967304679
    },
    {
      "weekday": "Monday",
      "hour": "22",
      "message_count": 1051,
      "positive_count": 221,
      "negative_count": 112,
      "neutral_count": 718,
      "total_sentiment_count": 109,
      "average_polarity": 0.04866518516943485,
      "average_subjectivity": 0.2005531477397408
    },
    {
      "weekday": "Monday",
      "hour": "23",
      "message_count": 619,
      "positive_count": 155,
      "negative_count": 71,
      "neutral_count": 393,
      "total_sentiment_count": 84,
      "average_polarity": 0.06131162111089412,
      "average_subjectivity": 0.23037739071644558
    },
    {
      "weekday": "Tuesday",
      "hour": "00",
      "message_count": 442,
      "positive_count": 101,
      "negative_count": 42,
      "neutral_count": 299,
      "total_sentiment_count": 59,
      "average_polarity": 0.049952545412104254,
      "average_subjectivity": 0.1980639465382112
    },
    {
      "weekday": "Tuesday",
      "hour": "01",
      "message_count": 262,
      "positive_count": 60,
      "negative_count": 38,
      "neutral_count": 164,
      "total_sentiment_count": 22,
      "average_polarity": 0.023576767539076688,
      "average_subjectivity": 0.21893072973464198
    },
    {
      "weekday": "Tuesday",
      "hour": "02",
      "message_count": 190,
      "positive_count": 44,
      "negative_count": 28,
      "neutral_count": 118,
      "total_sentiment_count": 16,
      "average_polarity": 0.040837005708716234,
      "average_subjectivity": 0.24742813631300478
    },
    {
      "weekday": "Tuesday",
      "hour": "03",
      "message_count": 34,
      "positive_count": 6,
      "negative_count": 8,
      "neutral_count": 20,
      "total_sentiment_count": -2,
      "average_polarity": 0.008210784313725489,
      "average_subjectivity": 0.2644199346405229
    },
    {
      "weekday": "Tuesday",
      "hour": "04",
      "message_count": 44,
      "positive_count": 10,
      "negative_count": 9,
      "neutral_count": 25,
      "total_sentiment_count": 1,
      "average_polarity": -0.004648760330578512,
      "average_subjectivity": 0.2959911616161616
    },
    {
      "weekday": "Tuesday",
      "hour": "05",
      "message_count": 222,
      "positive_count": 45,
      "negative_count": 16,
      "neutral_count": 161,
      "total_sentiment_count": 29,
      "average_polarity": 0.04946321321321321,
      "average_subjectivity": 0.1920947733447734
    },
    {
      "weekday": "Tuesday",
      "hour": "06",
      "message_count": 403,
      "positive_count": 77,
      "negative_count": 45,
      "neutral_count": 281,
      "total_sentiment_count": 32,
      "average_polarity": 0.03650384561674882,
      "average_subjectivity": 0.20114633126729903
    },
    {
      "weekday": "Tuesday",
      "hour": "07",
      "message_count": 410,
      "positive_count": 115,
      "negative_count": 42,
      "neutral_count": 253,
      "total_sentiment_count": 73,
      "average_polarity": 0.06157594674972725,
      "average_subjectivity": 0.23263376945998898
    },
    {
      "weekday": "Tuesday",
      "hour": "08",
      "message_count": 468,
      "positive_count": 116,
      "negative_count": 58,
      "neutral_count": 294,
      "total_sentiment_count": 58,
      "average_polarity": 0.05102080918053142,
      "average_subjectivity": 0.22755340803150623
    },
    {
      "weekday": "Tuesday",
      "hour": "09",
      "message_count": 605,
      "positive_count": 189,
      "negative_count": 68,
      "neutral_count": 348,
      "total_sentiment_count": 121,
      "average_polarity": 0.06918743803640506,
      "average_subjectivity": 0.2642391135876673
    },
    {
      "weekday": "Tuesday",
      "hour": "10",
      "message_count": 497,
      "positive_count": 135,
      "negative_count": 51,
      "neutral_count": 311,
      "total_sentiment_count": 84,
      "average_polarity": 0.07789329941241417,
      "average_subjectivity": 0.2520597754023307
    },
    {
      "weekday": "Tuesday",
      "hour": "11",
      "message_count": 560,
      "positive_count": 130,
      "negative_count": 55,
      "neutral_count": 375,
      "total_sentiment_count": 75,
      "average_polarity": 0.05373427998093177,
      "average_subjectivity": 0.21665044826205554
    },
    {
      "weekday": "Tuesday",
      "hour": "12",
      "message_count": 643,
      "positive_count": 161,
      "negative_count": 81,
      "neutral_count": 401,
      "total_sentiment_count": 80,
      "average_polarity": 0.0577826918352018,
      "average_subjectivity": 0.2298406263046837
    },
    {
      "weekday": "Tuesday",
      "hour": "13",
      "message_count": 1022,
      "positive_count": 249,
      "negative_count": 120,
      "neutral_count": 653,
      "total_sentiment_count": 129,
      "average_polarity": 0.0606011519842652,
      "average_subjectivity": 0.23221063964785432
    },
    {
      "weekday": "Tuesday",
      "hour": "14",
      "message_count": 1002,
      "positive_count": 216,
      "negative_count": 98,
      "neutral_count": 688,
      "total_sentiment_count": 118,
      "average_polarity": 0.0459177817405113,
      "average_subjectivity": 0.20716057273380137
    },
    {
      "weekday": "Tuesday",
      "hour": "15",
      "message_count": 1489,
      "positive_count": 319,
      "negative_count": 147,
      "neutral_count": 1023,
      "total_sentiment_count": 172,
      "average_polarity": 0.04890330061141006,
      "average_subjectivity": 0.1990775508827333
    },
    {
      "weekday": "Tuesday",
      "hour": "16",
      "message_count": 1362,
      "positive_count": 266,
      "negative_count": 109,
      "neutral_count": 987,
      "total_sentiment_count": 157,
      "average_polarity": 0.04935021213999744,
      "average_subjectivity": 0.17830757297442312
    },
    {
      "weekday": "Tuesday",
      "hour": "17",
      "message_count": 1338,
      "positive_count": 241,
      "negative_count": 134,
      "neutral_count": 963,
      "total_sentiment_count": 107,
      "average_polarity": 0.027684399919545667,
      "average_subjectivity": 0.1887535436073366
    },
    {
      "weekday": "Tuesday",
      "hour": "18",
      "message_count": 1470,
      "positive_count": 233,
      "negative_count": 127,
      "neutral_count": 1110,
      "total_sentiment_count": 106,
      "average_polarity": 0.03215841082103843,
      "average_subjectivity": 0.16525986161105213
    },
    {
      "weekday": "Tuesday",
      "hour": "19",
      "message_count": 1507,
      "positive_count": 234,
      "negative_count": 109,
      "neutral_count": 1164,
      "total_sentiment_count": 125,
      "average_polarity": 0.03535771251093256,
      "average_subjectivity": 0.14731114490848707
    },
    {
      "weekday": "Tuesday",
      "hour": "20",
      "message_count": 1061,
      "positive_count": 174,
      "negative_count": 98,
      "neutral_count": 789,
      "total_sentiment_count": 76,
      "average_polarity": 0.035557310005943386,
      "average_subjectivity": 0.1671750538008786
    },
    {
      "weekday": "Tuesday",
      "hour": "21",
      "message_count": 1063,
      "positive_count": 175,
      "negative_count": 92,
      "neutral_count": 796,
      "total_sentiment_count": 83,
      "average_polarity": 0.03216776446350766,
      "average_subjectivity": 0.16083569699350506
    },
    {
      "weekday": "Tuesday",
      "hour": "22",
      "message_count": 1074,
      "positive_count": 209,
      "negative_count": 98,
      "neutral_count": 767,
      "total_sentiment_count": 111,
      "average_polarity": 0.0444515692640693,
      "average_subjectivity": 0.17515364505657807
    },
    {
      "weekday": "Tuesday",
      "hour": "23",
      "message_count": 919,
      "positive_count": 228,
      "negative_count": 97,
      "neutral_count": 594,
      "total_sentiment_count": 131,
      "average_polarity": 0.05546747220695033,
      "average_subjectivity": 0.22055335878512272
    },
    {
      "weekday": "Wednesday",
      "hour": "00",
      "message_count": 609,
      "positive_count": 174,
      "negative_count": 63,
      "neutral_count": 372,
      "total_sentiment_count": 111,
      "average_polarity": 0.07544680041598392,
      "average_subjectivity": 0.22690163631254642
    },
    {
      "weekday": "Wednesday",
      "hour": "01",
      "message_count": 446,
      "positive_count": 99,
      "negative_count": 43,
      "neutral_count": 304,
      "total_sentiment_count": 56,
      "average_polarity": 0.04968022261744237,
      "average_subjectivity": 0.21681390555549745
    },
    {
      "weekday": "Wednesday",
      "hour": "02",
      "message_count": 242,
      "positive_count": 71,
      "negative_count": 30,
      "neutral_count": 141,
      "total_sentiment_count": 41,
      "average_polarity": 0.07777310442083166,
      "average_subjectivity": 0.2509750098386462
    },
    {
      "weekday": "Wednesday",
      "hour": "03",
      "message_count": 88,
      "positive_count": 32,
      "negative_count": 9,
      "neutral_count": 47,
      "total_sentiment_count": 23,
      "average_polarity": 0.09487362463924963,
      "average_subjectivity": 0.2488494318181819
    },
    {
      "weekday": "Wednesday",
      "hour": "04",
      "message_count": 42,
      "positive_count": 15,
      "negative_count": 5,
      "neutral_count": 22,
      "total_sentiment_count": 10,
      "average_polarity": 0.07002976190476191,
      "average_subjectivity": 0.2974250440917108
    },
    {
      "weekday": "Wednesday",
      "hour": "05",
      "message_count": 133,
      "positive_count": 33,
      "negative_count": 14,
      "neutral_count": 86,
      "total_sentiment_count": 19,
      "average_polarity": 0.06550739092629532,
      "average_subjectivity": 0.23028764513324126
    },
    {
      "weekday": "Wednesday",
      "hour": "06",
      "message_count": 264,
      "positive_count": 66,
      "negative_count": 44,
      "neutral_count": 154,
      "total_sentiment_count": 22,
      "average_polarity": 0.028172043304619063,
      "average_subjectivity": 0.2789329532700746
    },
    {
      "weekday": "Wednesday",
      "hour": "07",
      "message_count": 349,
      "positive_count": 91,
      "negative_count": 37,
      "neutral_count": 221,
      "total_sentiment_count": 54,
      "average_polarity": 0.05248796730172088,
      "average_subjectivity": 0.22671535868885437
    },
    {
      "weekday": "Wednesday",
      "hour": "08",
      "message_count": 536,
      "positive_count": 122,
      "negative_count": 60,
      "neutral_count": 354,
      "total_sentiment_count": 62,
      "average_polarity": 0.04951212608045631,
      "average_subjectivity": 0.22566302180924389
    },
    {
      "weekday": "Wednesday",
      "hour": "09",
      "message_count": 620,
      "positive_count": 124,
      "negative_count": 68,
      "neutral_count": 428,
      "total_sentiment_count": 56,
      "average_polarity": 0.04151088990907543,
      "average_subjectivity": 0.19472092129047772
    },
    {
      "weekday": "Wednesday",
      "hour": "10",
      "message_count": 564,
      "positive_count": 121,
      "negative_count": 41,
      "neutral_count": 402,
      "total_sentiment_count": 80,
      "average_polarity": 0.05340312348457299,
      "average_subjectivity": 0.17780157133548094
    },
    {
      "weekday": "Wednesday",
      "hour": "11",
      "message_count": 711,
      "positive_count": 170,
      "negative_count": 74,
      "neutral_count": 467,
      "total_sentiment_count": 96,
      "average_polarity": 0.05318535610126933,
      "average_subjectivity": 0.21916553177026343
    },
    {
      "weekday": "Wednesday",
      "hour": "12",
      "message_count": 924,
      "positive_count": 220,
      "negative_count": 97,
      "neutral_count": 607,
      "total_sentiment_count": 123,
      "average_polarity": 0.048058965505394076,
      "average_subjectivity": 0.2203845892963858
    },
    {
      "weekday": "Wednesday",
      "hour": "13",
      "message_count": 946,
      "positive_count": 208,
      "negative_count": 89,
      "neutral_count": 649,
      "total_sentiment_count": 119,
      "average_polarity": 0.055725577276845795,
      "average_subjectivity": 0.21697414406320326
    },
    {
      "weekday": "Wednesday",
      "hour": "14",
      "message_count": 944,
      "positive_count": 211,
      "negative_count": 95,
      "neutral_count": 638,
      "total_sentiment_count": 116,
      "average_polarity": 0.058233633258934096,
      "average_subjectivity": 0.20368264880934187
    },
    {
      "weekday": "Wednesday",
      "hour": "15",
      "message_count": 806,
      "positive_count": 171,
      "negative_count": 65,
      "neutral_count": 570,
      "total_sentiment_count": 106,
      "average_polarity": 0.05672695360195361,
      "average_subjectivity": 0.19404706516601675
    },
    {
      "weekday": "Wednesday",
      "hour": "16",
      "message_count": 756,
      "positive_count": 160,
      "negative_count": 76,
      "neutral_count": 520,
      "total_sentiment_count": 84,
      "average_polarity": 0.05287724957533163,
      "average_subjectivity": 0.20976525134428578
    },
    {
      "weekday": "Wednesday",
      "hour": "17",
      "message_count": 837,
      "positive_count": 167,
      "negative_count": 85,
      "neutral_count": 585,
      "total_sentiment_count": 82,
      "average_polarity": 0.03740742428839801,
      "average_subjectivity": 0.1959748254588459
    },
    {
      "weekday": "Wednesday",
      "hour": "18",
      "message_count": 1250,
      "positive_count": 266,
      "negative_count": 126,
      "neutral_count": 858,
      "total_sentiment_count": 140,
      "average_polarity": 0.04644856589706591,
      "average_subjectivity": 0.19775516664816659
    },
    {
      "weekday": "Wednesday",
      "hour": "19",
      "message_count": 1196,
      "positive_count": 183,
      "negative_count": 103,
      "neutral_count": 910,
      "total_sentiment_count": 80,
      "average_polarity": 0.030308590614297144,
      "average_subjectivity": 0.15797156144982236
    },
    {
      "weekday": "Wednesday",
      "hour": "20",
      "message_count": 1115,
      "positive_count": 208,
      "negative_count": 121,
      "neutral_count": 786,
      "total_sentiment_count": 87,
      "average_polarity": 0.034566578902537434,
      "average_subjectivity": 0.18763598640190574
    },
    {
      "weekday": "Wednesday",
      "hour": "21",
      "message_count": 1310,
      "positive_count": 282,
      "negative_count": 141,
      "neutral_count": 887,
      "total_sentiment_count": 141,
      "average_polarity": 0.05122862449255586,
      "average_subjectivity": 0.19626077435781633
    },
    {
      "weekday": "Wednesday",
      "hour": "22",
      "message_count": 779,
      "positive_count": 200,
      "negative_count": 91,
      "neutral_count": 488,
      "total_sentiment_count": 109,
      "average_polarity": 0.0591416944024454,
      "average_subjectivity": 0.23759406389621412
    },
    {
      "weekday": "Wednesday",
      "hour": "23",
      "message_count": 568,
      "positive_count": 133,
      "negative_count": 55,
      "neutral_count": 380,
      "total_sentiment_count": 78,
      "average_polarity": 0.0486607443993463,
      "average_subjectivity": 0.2054438275566554
    },
    {
      "weekday": "Thursday",
      "hour": "00",
      "message_count": 519,
      "positive_count": 116,
      "negative_count": 49,
      "neutral_count": 354,
      "total_sentiment_count": 67,
      "average_polarity": 0.055631042047227006,
      "average_subjectivity": 0.18351130230826762
    },
    {
      "weekday": "Thursday",
      "hour": "01",
      "message_count": 282,
      "positive_count": 56,
      "negative_count": 40,
      "neutral_count": 186,
      "total_sentiment_count": 16,
      "average_polarity": 0.031975004818533194,
      "average_subjectivity": 0.19814639663265554
    },
    {
      "weekday": "Thursday",
      "hour": "02",
      "message_count": 140,
      "positive_count": 40,
      "negative_count": 18,
      "neutral_count": 82,
      "total_sentiment_count": 22,
      "average_polarity": 0.07196943929086783,
      "average_subjectivity": 0.25202290764790775
    },
    {
      "weekday": "Thursday",
      "hour": "03",
      "message_count": 72,
      "positive_count": 16,
      "negative_count": 8,
      "neutral_count": 48,
      "total_sentiment_count": 8,
      "average_polarity": 0.051397156084656094,
      "average_subjectivity": 0.20949900793650789
    },
    {
      "weekday": "Thursday",
      "hour": "04",
      "message_count": 95,
      "positive_count": 22,
      "negative_count": 10,
      "neutral_count": 63,
      "total_sentiment_count": 12,
      "average_polarity": 0.04760044049517734,
      "average_subjectivity": 0.2118408816654431
    },
    {
      "weekday": "Thursday",
      "hour": "05",
      "message_count": 182,
      "positive_count": 49,
      "negative_count": 19,
      "neutral_count": 114,
      "total_sentiment_count": 30,
      "average_polarity": 0.07791175094746523,
      "average_subjectivity": 0.23423748412759396
    },
    {
      "weekday": "Thursday",
      "hour": "06",
      "message_count": 307,
      "positive_count": 70,
      "negative_count": 42,
      "neutral_count": 195,
      "total_sentiment_count": 28,
      "average_polarity": 0.048727807389859476,
      "average_subjectivity": 0.22719454869536307
    },
    {
      "weekday": "Thursday",
      "hour": "07",
      "message_count": 269,
      "positive_count": 57,
      "negative_count": 31,
      "neutral_count": 181,
      "total_sentiment_count": 26,
      "average_polarity": 0.05368324787562702,
      "average_subjectivity": 0.20358721606769942
    },
    {
      "weekday": "Thursday",
      "hour": "08",
      "message_count": 357,
      "positive_count": 76,
      "negative_count": 33,
      "neutral_count": 248,
      "total_sentiment_count": 43,
      "average_polarity": 0.056534767105495376,
      "average_subjectivity": 0.19378369698047568
    },
    {
      "weekday": "Thursday",
      "hour": "09",
      "message_count": 402,
      "positive_count": 124,
      "negative_count": 55,
      "neutral_count": 223,
      "total_sentiment_count": 69,
      "average_polarity": 0.07204232938841149,
      "average_subjectivity": 0.26459519756317024
    },
    {
      "weekday": "Thursday",
      "hour": "10",
      "message_count": 776,
      "positive_count": 165,
      "negative_count": 96,
      "neutral_count": 515,
      "total_sentiment_count": 69,
      "average_polarity": 0.04330481831517363,
      "average_subjectivity": 0.21174476909933454
    },
    {
      "weekday": "Thursday",
      "hour": "11",
      "message_count": 889,
      "positive_count": 193,
      "negative_count": 120,
      "neutral_count": 576,
      "total_sentiment_count": 73,
      "average_polarity": 0.03861195497936219,
      "average_subjectivity": 0.23137956261128353
    },
    {
      "weekday": "Thursday",
      "hour": "12",
      "message_count": 1052,
      "positive_count": 266,
      "negative_count": 117,
      "neutral_count": 669,
      "total_sentiment_count": 149,
      "average_polarity": 0.057911046059453866,
      "average_subjectivity": 0.23970403056227682
    },
    {
      "weekday": "Thursday",
      "hour": "13",
      "message_count": 815,
      "positive_count": 174,
      "negative_count": 72,
      "neutral_count": 569,
      "total_sentiment_count": 102,
      "average_polarity": 0.05270779073233065,
      "average_subjectivity": 0.1982266033784439
    },
    {
      "weekday": "Thursday",
      "hour": "14",
      "message_count": 1111,
      "positive_count": 255,
      "negative_count": 110,
      "neutral_count": 746,
      "total_sentiment_count": 145,
      "average_polarity": 0.05333173509450522,
      "average_subjectivity": 0.20646254668756914
    },
    {
      "weekday": "Thursday",
      "hour": "15",
      "message_count": 1078,
      "positive_count": 233,
      "negative_count": 87,
      "neutral_count": 758,
      "total_sentiment_count": 146,
      "average_polarity": 0.057310675053833755,
      "average_subjectivity": 0.19182128747875493
    },
    {
      "weekday": "Thursday",
      "hour": "16",
      "message_count": 1298,
      "positive_count": 263,
      "negative_count": 99,
      "neutral_count": 936,
      "total_sentiment_count": 164,
      "average_polarity": 0.050052734031932784,
      "average_subjectivity": 0.17946225406163763
    },
    {
      "weekday": "Thursday",
      "hour": "17",
      "message_count": 1050,
      "positive_count": 211,
      "negative_count": 112,
      "neutral_count": 727,
      "total_sentiment_count": 99,
      "average_polarity": 0.043929731923072285,
      "average_subjectivity": 0.19651668962197671
    },
    {
      "weekday": "Thursday",
      "hour": "18",
      "message_count": 1227,
      "positive_count": 227,
      "negative_count": 80,
      "neutral_count": 920,
      "total_sentiment_count": 147,
      "average_polarity": 0.04743060999992105,
      "average_subjectivity": 0.163827300766518
    },
    {
      "weekday": "Thursday",
      "hour": "19",
      "message_count": 1347,
      "positive_count": 252,
      "negative_count": 89,
      "neutral_count": 1006,
      "total_sentiment_count": 163,
      "average_polarity": 0.048967615000001824,
      "average_subjectivity": 0.17558111680930913
    },
    {
      "weekday": "Thursday",
      "hour": "20",
      "message_count": 1103,
      "positive_count": 236,
      "negative_count": 104,
      "neutral_count": 763,
      "total_sentiment_count": 132,
      "average_polarity": 0.04776237582051275,
      "average_subjectivity": 0.19339323856946247
    },
    {
      "weekday": "Thursday",
      "hour": "21",
      "message_count": 1076,
      "positive_count": 205,
      "negative_count": 79,
      "neutral_count": 792,
      "total_sentiment_count": 126,
      "average_polarity": 0.048202141860981824,
      "average_subjectivity": 0.16756668750983206
    },
    {
      "weekday": "Thursday",
      "hour": "22",
      "message_count": 786,
      "positive_count": 167,
      "negative_count": 75,
      "neutral_count": 544,
      "total_sentiment_count": 92,
      "average_polarity": 0.04228539828492118,
      "average_subjectivity": 0.19268262413300588
    },
    {
      "weekday": "Thursday",
      "hour": "23",
      "message_count": 873,
      "positive_count": 205,
      "negative_count": 108,
      "neutral_count": 560,
      "total_sentiment_count": 97,
      "average_polarity": 0.049164959728901836,
      "average_subjectivity": 0.22781909117083368
    },
    {
      "weekday": "Friday",
      "hour": "00",
      "message_count": 359,
      "positive_count": 91,
      "negative_count": 39,
      "neutral_count": 229,
      "total_sentiment_count": 52,
      "average_polarity": 0.058821475130667336,
      "average_subjectivity": 0.23391026929327757
    },
    {
      "weekday": "Friday",
      "hour": "01",
      "message_count": 216,
      "positive_count": 47,
      "negative_count": 29,
      "neutral_count": 140,
      "total_sentiment_count": 18,
      "average_polarity": 0.04686385459533606,
      "average_subjectivity": 0.23153935185185193
    },
    {
      "weekday": "Friday",
      "hour": "02",
      "message_count": 127,
      "positive_count": 29,
      "negative_count": 19,
      "neutral_count": 79,
      "total_sentiment_count": 10,
      "average_polarity": 0.04423012464351048,
      "average_subjectivity": 0.26441027257956384
    },
    {
      "weekday": "Friday",
      "hour": "03",
      "message_count": 31,
      "positive_count": 7,
      "negative_count": 6,
      "neutral_count": 18,
      "total_sentiment_count": 1,
      "average_polarity": 0.03694316436251923,
      "average_subjectivity": 0.25719406041986687
    },
    {
      "weekday": "Friday",
      "hour": "04",
      "message_count": 162,
      "positive_count": 39,
      "negative_count": 19,
      "neutral_count": 104,
      "total_sentiment_count": 20,
      "average_polarity": 0.0685736331569665,
      "average_subjectivity": 0.2603517538702724
    },
    {
      "weekday": "Friday",
      "hour": "05",
      "message_count": 352,
      "positive_count": 93,
      "negative_count": 50,
      "neutral_count": 209,
      "total_sentiment_count": 43,
      "average_polarity": 0.06710183770244225,
      "average_subjectivity": 0.2631210706747837
    },
    {
      "weekday": "Friday",
      "hour": "06",
      "message_count": 396,
      "positive_count": 107,
      "negative_count": 39,
      "neutral_count": 250,
      "total_sentiment_count": 68,
      "average_polarity": 0.07381759596090405,
      "average_subjectivity": 0.25022115685941443
    },
    {
      "weekday": "Friday",
      "hour": "07",
      "message_count": 454,
      "positive_count": 110,
      "negative_count": 39,
      "neutral_count": 305,
      "total_sentiment_count": 71,
      "average_polarity": 0.06256632462923765,
      "average_subjectivity": 0.2066402632894923
    },
    {
      "weekday": "Friday",
      "hour": "08",
      "message_count": 825,
      "positive_count": 180,
      "negative_count": 105,
      "neutral_count": 540,
      "total_sentiment_count": 75,
      "average_polarity": 0.030432215105321205,
      "average_subjectivity": 0.2212453147862239
    },
    {
      "weekday": "Friday",
      "hour": "09",
      "message_count": 622,
      "positive_count": 131,
      "negative_count": 64,
      "neutral_count": 427,
      "total_sentiment_count": 67,
      "average_polarity": 0.04464777295766044,
      "average_subjectivity": 0.20826759625393074
    },
    {
      "weekday": "Friday",
      "hour": "10",
      "message_count": 601,
      "positive_count": 143,
      "negative_count": 74,
      "neutral_count": 384,
      "total_sentiment_count": 69,
      "average_polarity": 0.04298710902704248,
      "average_subjectivity": 0.22835303800778023
    },
    {
      "weekday": "Friday",
      "hour": "11",
      "message_count": 646,
      "positive_count": 146,
      "negative_count": 73,
      "neutral_count": 427,
      "total_sentiment_count": 73,
      "average_polarity": 0.041803875776786,
      "average_subjectivity": 0.22576920130093514
    },
    {
      "weekday": "Friday",
      "hour": "12",
      "message_count": 979,
      "positive_count": 215,
      "negative_count": 113,
      "neutral_count": 651,
      "total_sentiment_count": 102,
      "average_polarity": 0.03968849660481065,
      "average_subjectivity": 0.2106021548966243
    },
    {
      "weekday": "Friday",
      "hour": "13",
      "message_count": 915,
      "positive_count": 217,
      "negative_count": 111,
      "neutral_count": 587,
      "total_sentiment_count": 106,
      "average_polarity": 0.04878842072971305,
      "average_subjectivity": 0.21822163281118642
    },
    {
      "weekday": "Friday",
      "hour": "14",
      "message_count": 784,
      "positive_count": 168,
      "negative_count": 80,
      "neutral_count": 536,
      "total_sentiment_count": 88,
      "average_polarity": 0.05354152379295878,
      "average_subjectivity": 0.21025544545920824
    },
    {
      "weekday": "Friday",
      "hour": "15",
      "message_count": 1068,
      "positive_count": 214,
      "negative_count": 110,
      "neutral_count": 744,
      "total_sentiment_count": 104,
      "average_polarity": 0.03878395320694011,
      "average_subjectivity": 0.1980609195215936
    },
    {
      "weekday": "Friday",
      "hour": "16",
      "message_count": 1134,
      "positive_count": 227,
      "negative_count": 140,
      "neutral_count": 767,
      "total_sentiment_count": 87,
      "average_polarity": 0.03661487613213675,
      "average_subjectivity": 0.21239893225556922
    },
    {
      "weekday": "Friday",
      "hour": "17",
      "message_count": 858,
      "positive_count": 188,
      "negative_count": 82,
      "neutral_count": 588,
      "total_sentiment_count": 106,
      "average_polarity": 0.04615221840017883,
      "average_subjectivity": 0.20550990023746446
    },
    {
      "weekday": "Friday",
      "hour": "18",
      "message_count": 1196,
      "positive_count": 238,
      "negative_count": 108,
      "neutral_count": 850,
      "total_sentiment_count": 130,
      "average_polarity": 0.04754991319444449,
      "average_subjectivity": 0.1945921786546786
    },
    {
      "weekday": "Friday",
      "hour": "19",
      "message_count": 1293,
      "positive_count": 225,
      "negative_count": 103,
      "neutral_count": 965,
      "total_sentiment_count": 122,
      "average_polarity": 0.040420718911148165,
      "average_subjectivity": 0.1702246983151027
    },
    {
      "weekday": "Friday",
      "hour": "20",
      "message_count": 1031,
      "positive_count": 201,
      "negative_count": 113,
      "neutral_count": 717,
      "total_sentiment_count": 88,
      "average_polarity": 0.03859742388297576,
      "average_subjectivity": 0.19390213275495255
    },
    {
      "weekday": "Friday",
      "hour": "21",
      "message_count": 1277,
      "positive_count": 237,
      "negative_count": 139,
      "neutral_count": 901,
      "total_sentiment_count": 98,
      "average_polarity": 0.03319799363232634,
      "average_subjectivity": 0.189761902542275
    },
    {
      "weekday": "Friday",
      "hour": "22",
      "message_count": 908,
      "positive_count": 161,
      "negative_count": 71,
      "neutral_count": 676,
      "total_sentiment_count": 90,
      "average_polarity": 0.04006139410943928,
      "average_subjectivity": 0.1560068401271596
    },
    {
      "weekday": "Friday",
      "hour": "23",
      "message_count": 391,
      "positive_count": 111,
      "negative_count": 46,
      "neutral_count": 234,
      "total_sentiment_count": 65,
      "average_polarity": 0.06075366839753031,
      "average_subjectivity": 0.2471514499519615
    },
    {
      "weekday": "Saturday",
      "hour": "00",
      "message_count": 377,
      "positive_count": 94,
      "negative_count": 40,
      "neutral_count": 243,
      "total_sentiment_count": 54,
      "average_polarity": 0.05658057459781595,
      "average_subjectivity": 0.2439535793315635
    },
    {
      "weekday": "Saturday",
      "hour": "01",
      "message_count": 507,
      "positive_count": 135,
      "negative_count": 56,
      "neutral_count": 316,
      "total_sentiment_count": 79,
      "average_polarity": 0.06722319703088936,
      "average_subjectivity": 0.24794093133836717
    },
    {
      "weekday": "Saturday",
      "hour": "02",
      "message_count": 186,
      "positive_count": 56,
      "negative_count": 23,
      "neutral_count": 107,
      "total_sentiment_count": 33,
      "average_polarity": 0.0748376623376623,
      "average_subjectivity": 0.22754013832642872
    },
    {
      "weekday": "Saturday",
      "hour": "03",
      "message_count": 104,
      "positive_count": 21,
      "negative_count": 15,
      "neutral_count": 68,
      "total_sentiment_count": 6,
      "average_polarity": 0.02937487859362859,
      "average_subjectivity": 0.221230072011322
    },
    {
      "weekday": "Saturday",
      "hour": "04",
      "message_count": 57,
      "positive_count": 16,
      "negative_count": 6,
      "neutral_count": 35,
      "total_sentiment_count": 10,
      "average_polarity": 0.06326532872585505,
      "average_subjectivity": 0.20525983519404575
    },
    {
      "weekday": "Saturday",
      "hour": "05",
      "message_count": 96,
      "positive_count": 26,
      "negative_count": 10,
      "neutral_count": 60,
      "total_sentiment_count": 16,
      "average_polarity": 0.09967053345959598,
      "average_subjectivity": 0.2288362606721982
    },
    {
      "weekday": "Saturday",
      "hour": "06",
      "message_count": 137,
      "positive_count": 29,
      "negative_count": 14,
      "neutral_count": 94,
      "total_sentiment_count": 15,
      "average_polarity": 0.05978543582330079,
      "average_subjectivity": 0.1846521019194377
    },
    {
      "weekday": "Saturday",
      "hour": "07",
      "message_count": 233,
      "positive_count": 46,
      "negative_count": 34,
      "neutral_count": 153,
      "total_sentiment_count": 12,
      "average_polarity": 0.028480970031399218,
      "average_subjectivity": 0.22446965826257667
    },
    {
      "weekday": "Saturday",
      "hour": "08",
      "message_count": 320,
      "positive_count": 77,
      "negative_count": 35,
      "neutral_count": 208,
      "total_sentiment_count": 42,
      "average_polarity": 0.06406719820977633,
      "average_subjectivity": 0.22150156513047126
    },
    {
      "weekday": "Saturday",
      "hour": "09",
      "message_count": 533,
      "positive_count": 137,
      "negative_count": 40,
      "neutral_count": 356,
      "total_sentiment_count": 97,
      "average_polarity": 0.06923236533027809,
      "average_subjectivity": 0.2022919284436639
    },
    {
      "weekday": "Saturday",
      "hour": "10",
      "message_count": 647,
      "positive_count": 128,
      "negative_count": 55,
      "neutral_count": 464,
      "total_sentiment_count": 73,
      "average_polarity": 0.04173221844969466,
      "average_subjectivity": 0.18286284627612998
    },
    {
      "weekday": "Saturday",
      "hour": "11",
      "message_count": 768,
      "positive_count": 169,
      "negative_count": 81,
      "neutral_count": 518,
      "total_sentiment_count": 88,
      "average_polarity": 0.04513560714657026,
      "average_subjectivity": 0.21847338907142577
    },
    {
      "weekday": "Saturday",
      "hour": "12",
      "message_count": 734,
      "positive_count": 136,
      "negative_count": 65,
      "neutral_count": 533,
      "total_sentiment_count": 71,
      "average_polarity": 0.042534159770753324,
      "average_subjectivity": 0.1761391999620424
    },
    {
      "weekday": "Saturday",
      "hour": "13",
      "message_count": 938,
      "positive_count": 199,
      "negative_count": 84,
      "neutral_count": 655,
      "total_sentiment_count": 115,
      "average_polarity": 0.04442783249286452,
      "average_subjectivity": 0.1902341761207508
    },
    {
      "weekday": "Saturday",
      "hour": "14",
      "message_count": 932,
      "positive_count": 213,
      "negative_count": 87,
      "neutral_count": 632,
      "total_sentiment_count": 126,
      "average_polarity": 0.05000467784764234,
      "average_subjectivity": 0.20332032257997934
    },
    {
      "weekday": "Saturday",
      "hour": "15",
      "message_count": 852,
      "positive_count": 187,
      "negative_count": 77,
      "neutral_count": 588,
      "total_sentiment_count": 110,
      "average_polarity": 0.04490428683210376,
      "average_subjectivity": 0.1928881663061044
    },
    {
      "weekday": "Saturday",
      "hour": "16",
      "message_count": 878,
      "positive_count": 179,
      "negative_count": 67,
      "neutral_count": 632,
      "total_sentiment_count": 112,
      "average_polarity": 0.061511220445588356,
      "average_subjectivity": 0.1884981831685988
    },
    {
      "weekday": "Saturday",
      "hour": "17",
      "message_count": 898,
      "positive_count": 163,
      "negative_count": 70,
      "neutral_count": 665,
      "total_sentiment_count": 93,
      "average_polarity": 0.042025522887159876,
      "average_subjectivity": 0.1628697035044473
    },
    {
      "weekday": "Saturday",
      "hour": "18",
      "message_count": 1137,
      "positive_count": 183,
      "negative_count": 74,
      "neutral_count": 880,
      "total_sentiment_count": 109,
      "average_polarity": 0.040634369781950855,
      "average_subjectivity": 0.15340997662176328
    },
    {
      "weekday": "Saturday",
      "hour": "19",
      "message_count": 1100,
      "positive_count": 168,
      "negative_count": 78,
      "neutral_count": 854,
      "total_sentiment_count": 90,
      "average_polarity": 0.03480001721763087,
      "average_subjectivity": 0.1417591988609034
    },
    {
      "weekday": "Saturday",
      "hour": "20",
      "message_count": 1317,
      "positive_count": 253,
      "negative_count": 133,
      "neutral_count": 931,
      "total_sentiment_count": 120,
      "average_polarity": 0.03838106328334453,
      "average_subjectivity": 0.1870440642056387
    },
    {
      "weekday": "Saturday",
      "hour": "21",
      "message_count": 1306,
      "positive_count": 256,
      "negative_count": 137,
      "neutral_count": 913,
      "total_sentiment_count": 119,
      "average_polarity": 0.04610927145000658,
      "average_subjectivity": 0.19108590439323603
    },
    {
      "weekday": "Saturday",
      "hour": "22",
      "message_count": 928,
      "positive_count": 163,
      "negative_count": 84,
      "neutral_count": 681,
      "total_sentiment_count": 79,
      "average_polarity": 0.03222018133925462,
      "average_subjectivity": 0.17888909362508504
    },
    {
      "weekday": "Saturday",
      "hour": "23",
      "message_count": 816,
      "positive_count": 194,
      "negative_count": 85,
      "neutral_count": 537,
      "total_sentiment_count": 109,
      "average_polarity": 0.04751562993673904,
      "average_subjectivity": 0.21516929820927969
    },
    {
      "weekday": "Sunday",
      "hour": "00",
      "message_count": 511,
      "positive_count": 124,
      "negative_count": 57,
      "neutral_count": 330,
      "total_sentiment_count": 67,
      "average_polarity": 0.04928460414884096,
      "average_subjectivity": 0.21160605389935136
    },
    {
      "weekday": "Sunday",
      "hour": "01",
      "message_count": 281,
      "positive_count": 75,
      "negative_count": 46,
      "neutral_count": 160,
      "total_sentiment_count": 29,
      "average_polarity": 0.042640296799549456,
      "average_subjectivity": 0.2759730160441905
    },
    {
      "weekday": "Sunday",
      "hour": "02",
      "message_count": 119,
      "positive_count": 42,
      "negative_count": 21,
      "neutral_count": 56,
      "total_sentiment_count": 21,
      "average_polarity": 0.05166148277492815,
      "average_subjectivity": 0.32472778505341515
    },
    {
      "weekday": "Sunday",
      "hour": "03",
      "message_count": 5,
      "positive_count": 2,
      "negative_count": 1,
      "neutral_count": 2,
      "total_sentiment_count": 1,
      "average_polarity": 0.17642857142857143,
      "average_subjectivity": 0.34488095238095234
    },
    {
      "weekday": "Sunday",
      "hour": "04",
      "message_count": 62,
      "positive_count": 17,
      "negative_count": 4,
      "neutral_count": 41,
      "total_sentiment_count": 13,
      "average_polarity": 0.07237414467253175,
      "average_subjectivity": 0.2179851555254781
    },
    {
      "weekday": "Sunday",
      "hour": "05",
      "message_count": 215,
      "positive_count": 55,
      "negative_count": 34,
      "neutral_count": 126,
      "total_sentiment_count": 21,
      "average_polarity": 0.036249836403906166,
      "average_subjectivity": 0.27494717524077983
    },
    {
      "weekday": "Sunday",
      "hour": "06",
      "message_count": 276,
      "positive_count": 78,
      "negative_count": 33,
      "neutral_count": 165,
      "total_sentiment_count": 45,
      "average_polarity": 0.06293781827069868,
      "average_subjectivity": 0.2623970140500938
    },
    {
      "weekday": "Sunday",
      "hour": "07",
      "message_count": 291,
      "positive_count": 81,
      "negative_count": 43,
      "neutral_count": 167,
      "total_sentiment_count": 38,
      "average_polarity": 0.05372930954116518,
      "average_subjectivity": 0.2778949196088372
    },
    {
      "weekday": "Sunday",
      "hour": "08",
      "message_count": 533,
      "positive_count": 127,
      "negative_count": 72,
      "neutral_count": 334,
      "total_sentiment_count": 55,
      "average_polarity": 0.0419123398056325,
      "average_subjectivity": 0.25134313360532884
    },
    {
      "weekday": "Sunday",
      "hour": "09",
      "message_count": 688,
      "positive_count": 146,
      "negative_count": 64,
      "neutral_count": 478,
      "total_sentiment_count": 82,
      "average_polarity": 0.05115361594558546,
      "average_subjectivity": 0.19756880255699313
    },
    {
      "weekday": "Sunday",
      "hour": "10",
      "message_count": 771,
      "positive_count": 123,
      "negative_count": 69,
      "neutral_count": 579,
      "total_sentiment_count": 54,
      "average_polarity": 0.02385553995111387,
      "average_subjectivity": 0.15930134270722793
    },
    {
      "weekday": "Sunday",
      "hour": "11",
      "message_count": 803,
      "positive_count": 173,
      "negative_count": 83,
      "neutral_count": 547,
      "total_sentiment_count": 90,
      "average_polarity": 0.04440150926802549,
      "average_subjectivity": 0.20041336140106386
    },
    {
      "weekday": "Sunday",
      "hour": "12",
      "message_count": 1296,
      "positive_count": 254,
      "negative_count": 115,
      "neutral_count": 927,
      "total_sentiment_count": 139,
      "average_polarity": 0.04648660190760886,
      "average_subjectivity": 0.17944293703552947
    },
    {
      "weekday": "Sunday",
      "hour": "13",
      "message_count": 1175,
      "positive_count": 188,
      "negative_count": 115,
      "neutral_count": 872,
      "total_sentiment_count": 73,
      "average_polarity": 0.030676677892635364,
      "average_subjectivity": 0.17174086859554932
    },
    {
      "weekday": "Sunday",
      "hour": "14",
      "message_count": 1156,
      "positive_count": 204,
      "negative_count": 89,
      "neutral_count": 863,
      "total_sentiment_count": 115,
      "average_polarity": 0.046801529881114697,
      "average_subjectivity": 0.1655491872922669
    },
    {
      "weekday": "Sunday",
      "hour": "15",
      "message_count": 1088,
      "positive_count": 210,
      "negative_count": 94,
      "neutral_count": 784,
      "total_sentiment_count": 116,
      "average_polarity": 0.039750245031724814,
      "average_subjectivity": 0.18143541433829422
    },
    {
      "weekday": "Sunday",
      "hour": "16",
      "message_count": 761,
      "positive_count": 149,
      "negative_count": 59,
      "neutral_count": 553,
      "total_sentiment_count": 90,
      "average_polarity": 0.04826650376201765,
      "average_subjectivity": 0.1776966054244008
    },
    {
      "weekday": "Sunday",
      "hour": "17",
      "message_count": 1097,
      "positive_count": 187,
      "negative_count": 87,
      "neutral_count": 823,
      "total_sentiment_count": 100,
      "average_polarity": 0.03718506412558373,
      "average_subjectivity": 0.16243231691499696
    },
    {
      "weekday": "Sunday",
      "hour": "18",
      "message_count": 1006,
      "positive_count": 183,
      "negative_count": 100,
      "neutral_count": 723,
      "total_sentiment_count": 83,
      "average_polarity": 0.03417572774034007,
      "average_subjectivity": 0.18100183901401604
    },
    {
      "weekday": "Sunday",
      "hour": "19",
      "message_count": 1171,
      "positive_count": 239,
      "negative_count": 134,
      "neutral_count": 798,
      "total_sentiment_count": 105,
      "average_polarity": 0.036714864270372405,
      "average_subjectivity": 0.2069275603930813
    },
    {
      "weekday": "Sunday",
      "hour": "20",
      "message_count": 1036,
      "positive_count": 160,
      "negative_count": 68,
      "neutral_count": 808,
      "total_sentiment_count": 92,
      "average_polarity": 0.03592034520605949,
      "average_subjectivity": 0.1371828819373461
    },
    {
      "weekday": "Sunday",
      "hour": "21",
      "message_count": 1559,
      "positive_count": 237,
      "negative_count": 125,
      "neutral_count": 1197,
      "total_sentiment_count": 112,
      "average_polarity": 0.032484930804189474,
      "average_subjectivity": 0.15115542007155683
    },
    {
      "weekday": "Sunday",
      "hour": "22",
      "message_count": 1164,
      "positive_count": 215,
      "negative_count": 119,
      "neutral_count": 830,
      "total_sentiment_count": 96,
      "average_polarity": 0.04188747982401336,
      "average_subjectivity": 0.17864188078212984
    },
    {
      "weekday": "Sunday",
      "hour": "23",
      "message_count": 783,
      "positive_count": 183,
      "negative_count": 78,
      "neutral_count": 522,
      "total_sentiment_count": 105,
      "average_polarity": 0.04277175587999346,
      "average_subjectivity": 0.21110926529125754
    }
  ]
}